kitchenai/__init__.py
kitchenai/__main__.py
kitchenai/__version__.py
kitchenai/adapters.py
kitchenai/api.py
kitchenai/asgi.py
kitchenai/context_processors.py
kitchenai/settings.py
kitchenai/urls.py
kitchenai/wsgi.py
kitchenai/bento/__init__.py
kitchenai/bento/admin.py
kitchenai/bento/apps.py
kitchenai/bento/bento_config.py
kitchenai/bento/manager.py
kitchenai/bento/models.py
kitchenai/bento/types.py
kitchenai/bento/utils.py
kitchenai/bento/cli/__init__.py
kitchenai/bento/cli/bento.py
kitchenai/bento/cli/remote.py
kitchenai/bento/migrations/0001_initial.py
kitchenai/bento/migrations/0002_remoteclient_last_seen.py
kitchenai/bento/migrations/0003_alter_remoteclient_unique_together_and_more.py
kitchenai/bento/migrations/__init__.py
kitchenai/bento/templates/bento/pages/settings.html
kitchenai/cli/__init__.py
kitchenai/cli/main.py
kitchenai/cli/client/__init__.py
kitchenai/cli/client/client.py
kitchenai/contrib/__init__.py
kitchenai/contrib/kitchenai_sdk/__init__.py
kitchenai/contrib/kitchenai_sdk/base.py
kitchenai/contrib/kitchenai_sdk/hooks.py
kitchenai/contrib/kitchenai_sdk/kitchenai.py
kitchenai/contrib/kitchenai_sdk/schema.py
kitchenai/contrib/kitchenai_sdk/tasks.py
kitchenai/contrib/kitchenai_sdk/taxonomy/__init__.py
kitchenai/contrib/kitchenai_sdk/taxonomy/agent.py
kitchenai/contrib/kitchenai_sdk/taxonomy/embeddings.py
kitchenai/contrib/kitchenai_sdk/taxonomy/query.py
kitchenai/contrib/kitchenai_sdk/taxonomy/storage.py
kitchenai/contrib/notebooks/__init__.py
kitchenai/contrib/notebooks/notebooks.py
kitchenai/core/__init__.py
kitchenai/core/activities.py
kitchenai/core/adapters.py
kitchenai/core/admin.py
kitchenai/core/agents.py
kitchenai/core/apps.py
kitchenai/core/exceptions.py
kitchenai/core/forms.py
kitchenai/core/middleware.py
kitchenai/core/router.py
kitchenai/core/signals.py
kitchenai/core/temporal.py
kitchenai/core/temporal_utils.py
kitchenai/core/tools.py
kitchenai/core/types.py
kitchenai/core/urls.py
kitchenai/core/utils.py
kitchenai/core/views.py
kitchenai-0.16.0.dist-info/METADATA
kitchenai-0.16.0.dist-info/WHEEL
kitchenai-0.16.0.dist-info/entry_points.txt
kitchenai-0.16.0.dist-info/licenses/LICENSE
kitchenai-0.16.0.dist-info/RECORD
