Metadata-Version: 2.4
Name: kitchenai
Version: 0.16.0
Author-email: epuerta <esteban_puerta@rhinosearch.io>
License-File: LICENSE
Classifier: Programming Language :: Python :: 3 :: Only
Classifier: Programming Language :: Python :: 3.11
Classifier: Programming Language :: Python :: 3.12
Requires-Python: >=3.11
Requires-Dist: aiohttp
Requires-Dist: boto3
Requires-Dist: cookiecutter
Requires-Dist: crispy-tailwind
Requires-Dist: diskcache
Requires-Dist: django-allauth-ui
Requires-Dist: django-allauth[socialaccount]
Requires-Dist: django-anymail[resend]
Requires-Dist: django-compressor
Requires-Dist: django-eventstream
Requires-Dist: django-extensions
Requires-Dist: django-health-check
Requires-Dist: django-htmx
Requires-Dist: django-lifecycle
Requires-Dist: django-model-utils
Requires-Dist: django-ninja
Requires-Dist: django-q-registry
Requires-Dist: django-q2
Requires-Dist: django-redis
Requires-Dist: django-storages[s3]
Requires-Dist: django-tailwind-cli
Requires-Dist: django-template-partials
Requires-Dist: django-unique-user-email
Requires-Dist: django-widget-tweaks
Requires-Dist: django[argon2]
Requires-Dist: djp
Requires-Dist: environs[django]
Requires-Dist: falco-toolbox
Requires-Dist: falco-ui
Requires-Dist: faststream[nats]
Requires-Dist: gunicorn
Requires-Dist: heroicons[django]
Requires-Dist: honcho
Requires-Dist: kitchenai-py
Requires-Dist: kitchenai-whisk
Requires-Dist: llama-index
Requires-Dist: markdown2
Requires-Dist: nbconvert
Requires-Dist: nbformat
Requires-Dist: nest-asyncio
Requires-Dist: pillow
Requires-Dist: posthog
Requires-Dist: psycopg[binary]
Requires-Dist: pyyaml
Requires-Dist: redis
Requires-Dist: refreshcss
Requires-Dist: rich
Requires-Dist: sentry-sdk
Requires-Dist: slippers
Requires-Dist: starlette
Requires-Dist: temporalio
Requires-Dist: typer
Requires-Dist: uvicorn
Requires-Dist: whitenoise
